nimrod/__init__.py
nimrod/nimrod.py
nimrod-0.1.0.dist-info/DESCRIPTION.rst
nimrod-0.1.0.dist-info/METADATA
nimrod-0.1.0.dist-info/RECORD
nimrod-0.1.0.dist-info/WHEEL
nimrod-0.1.0.dist-info/metadata.json
nimrod-0.1.0.dist-info/top_level.txt
